pokemonlib/__init__.py
pokemonlib/Core/Combat.py
pokemonlib/Core/Player.py
pokemonlib/Core/Pokemon.py
pokemonlib/Core/SaveUtils.py
pokemonlib/Core/__init__.py
pokemonlib/Engine/UIClass.py
pokemonlib/Engine/__init__.py
pokemonlib/cli/__init__.py
pokemonlib/cli/pokeproject.py
pokemonlib/misc/Exeptions.py
pokemonlib/misc/Security.py
pokemonlib/misc/Settings.py
pokemonlib/misc/__init__.py
pokemonlib/pokemonDataDownload/GetPokeAPI.py
pokemonlib/pokemonDataDownload/__init__.py
pokemonlib-0.0.5.dist-info/LICENSE
pokemonlib-0.0.5.dist-info/METADATA
pokemonlib-0.0.5.dist-info/WHEEL
pokemonlib-0.0.5.dist-info/entry_points.txt
pokemonlib-0.0.5.dist-info/top_level.txt
pokemonlib-0.0.5.dist-info/RECORD
