Metadata-Version: 2.1
Name: pokemonlib
Version: 0.0.5
Summary: An implementation of pokemon algorithms
Home-page: https://github.com/arthuro555/pokemonlib
Author: arthuro555
Author-email: papinrouge@gmail.com
License: UNKNOWN
Project-URL: Say Thanks!, https://saythanks.io/to/arthuro555
Project-URL: Source, https://github.com/arthuro555/pokemonlib
Platform: UNKNOWN
Classifier: Development Status :: 3 - Alpha
Classifier: Intended Audience :: Developers
Classifier: Programming Language :: Python :: 3
Classifier: Topic :: Software Development
Classifier: License :: OSI Approved :: MIT License
Classifier: Operating System :: OS Independent
Requires-Dist: requests
